{"interestingcomments": [{"Unnamed: 0": 131664, "autor": "cakeboyplum", "date": 1532608109000, "content": "Canon C200 joystick mapping /!/ Is there a way to map controls to the joystick on the c200 (like the c100) \n\nLike being able to control iso, shutter speed, temp all from clicking in the joystick and not having to first press the function button? \n\nThanks guys! ", "link": "https://www.reddit.com/r/canon/comments/921tmu/canon_c200_joystick_mapping/", "origin": "Reddit", "suborigin": "canon", "result": true, "Selector": "map", "selectorShort": "map", "MarkedSent": "canon c200 joystick mapping /!/ is there a way to -----> map !!!  controls to the joystick on the c200 (like the c100) \n\nlike being able to control iso, shutter speed, temp all from clicking in the joystick and not having to first press the function button? \n\nthanks guys! ", "sortedWord": "None", "identifyer": 22381, "year": "2018"}], "name": "mapcanon2018"}