{"interestingcomments": [{"Unnamed: 0": 265, "Relevance": 81.37, "content": "Blurry Image? What do I have to change?", "autor": "Dusiio", "date": 1564517551000, "link": "https://www.reddit.com/r/canon/comments/cjxcu3/blurry_image_what_do_i_have_to_change/", "origin": "Reddit", "suborigin": "canon", "result": false, "selectorShort": "None", "MarkedSent": "Blurry Image? What do I have to change?", "sortedWord": "None", "identifyer": 55554, "searchterm": "image clustering", "wiki_plot_tokenized": "['blurry', 'image', 'change']", "scores": "{'neg': 0.201, 'neu': 0.799, 'pos': 0.0, 'compound': -0.1926}", "Sentiment": "negative", "TB_score": null, "Emotion": null, "temp_list": null, "year": "2019"}], "name": "image clusteringcanon2019negative"}