{"interestingcomments": [{"Unnamed: 0": 153, "Relevance": 54.04, "content": "Any guesses on the rf 70-200 f/4 /!/ When it might debut, etc", "autor": "sour_creme", "date": 1596391821000, "link": "https://www.reddit.com/r/canon/comments/i2gnbk/any_guesses_on_the_rf_70200_f4/", "origin": "Reddit", "suborigin": "canon", "result": false, "selectorShort": "None", "MarkedSent": "Any guesses on the rf 70-200 f/4 /!/ When it might debut, etc", "sortedWord": "None", "identifyer": 46794, "searchterm": "Sorting tasks", "wiki_plot_tokenized": "['guess', 'debut', 'etc']", "scores": "{'neg': 0.0, 'neu': 1.0, 'pos': 0.0, 'compound': 0.0}", "Sentiment": "neutral", "TB_score": null, "Emotion": null, "temp_list": null, "year": "2020"}], "name": "Sorting taskscanon2020neutral"}